pysearch_mcp/__init__.py
pysearch_mcp/__main__.py
pysearch_mcp/mcp.py
pysearch_mcp/search_index.py
pysearch_mcp-0.1.0.dist-info/METADATA
pysearch_mcp-0.1.0.dist-info/WHEEL
pysearch_mcp-0.1.0.dist-info/entry_points.txt
pysearch_mcp-0.1.0.dist-info/licenses/LICENSE
pysearch_mcp-0.1.0.dist-info/RECORD
