Metadata-Version: 2.4
Name: pysearch_mcp
Version: 0.1.0
Summary: MCP stdio server for indexing venvs and searching from those or preexisting indexes
Project-URL: Homepage, https://github.com/mn-90/pysearch_mcp
Project-URL: Repository, https://github.com/mn-90/pysearch_mcp
Project-URL: Issues, https://github.com/mn-90/pysearch_mcp/issues
Author: Michael Neumeier
License: MIT License
License-File: LICENSE
Keywords: documentation,lunr,mcp,model-context-protocol,python,search
Classifier: Development Status :: 3 - Alpha
Classifier: Intended Audience :: Developers
Classifier: License :: OSI Approved :: MIT License
Classifier: Programming Language :: Python :: 3
Classifier: Programming Language :: Python :: 3.10
Classifier: Programming Language :: Python :: 3.11
Classifier: Programming Language :: Python :: 3.12
Classifier: Programming Language :: Python :: 3.13
Classifier: Programming Language :: Python :: 3.14
Classifier: Topic :: Software Development :: Libraries :: Python Modules
Requires-Python: >=3.10
Requires-Dist: fastmcp>=2.14.0
Requires-Dist: lunr==0.8.0
